btleWeatherStation/__init__.py
btleWeatherStation/__main__.py
btleWeatherStation/scan.py
btleWeatherStation/station.py
btleWeatherStation-3.1.0.dist-info/LICENSE
btleWeatherStation-3.1.0.dist-info/METADATA
btleWeatherStation-3.1.0.dist-info/WHEEL
btleWeatherStation-3.1.0.dist-info/top_level.txt
btleWeatherStation-3.1.0.dist-info/RECORD
