Metadata-Version: 2.1
Name: btleWeatherStation
Version: 3.1.0
Summary: Scan for and get data from an Oregon Scientific BtLE weather station
Home-page: https://github.com/mincebert/bleWeatherStation
Author: Arnaud Balmelle & Robert Franklin
Author-email: rcf@mince.net
Classifier: Programming Language :: Python :: 3
Classifier: License :: OSI Approved :: MIT License
Classifier: Operating System :: OS Independent
License-File: LICENSE
Requires-Dist: bluepy
